ridepy/cli.py
ridepy/__main__.py
ridepy/vehicle_state.py
ridepy/__init__.py
ridepy/events.py
ridepy/data_structures.py
ridepy/fleet_state.py
ridepy/data_structures_cython/data_structures.pxd
ridepy/data_structures_cython/data_structures.pyx
ridepy/data_structures_cython/__init__.py
ridepy/data_structures_cython/cdata_structures.h
ridepy/data_structures_cython/cdata_structures.pxd
ridepy/data_structures_cython/data_structures.cpython-39-x86_64-linux-gnu.so
ridepy/extras/simulation_set.py
ridepy/extras/io.py
ridepy/extras/spaces.py
ridepy/extras/__init__.py
ridepy/extras/io_utils.py
ridepy/cpp/main.cxx
ridepy/cpp/ridepy/spaces.h
ridepy/cpp/ridepy/dispatchers.h
ridepy/cpp/ridepy/datastructures.h
ridepy/cpp/ridepy/transportspace.h
ridepy/cpp/ridepy/vehiclestate.h
ridepy/util/spaces.py
ridepy/util/__init__.py
ridepy/util/testing_utils.py
ridepy/util/request_generators.py
ridepy/util/dispatchers_cython/cdispatchers.pxd
ridepy/util/dispatchers_cython/cdispatchers.pyx
ridepy/util/dispatchers_cython/cdispatchers.cpython-39-x86_64-linux-gnu.so
ridepy/util/dispatchers_cython/__init__.py
ridepy/util/dispatchers_cython/dispatchers.pyx
ridepy/util/dispatchers_cython/cdispatchers_utils.h
ridepy/util/dispatchers_cython/dispatchers.pxd
ridepy/util/dispatchers_cython/cdispatchers.h
ridepy/util/dispatchers_cython/dispatchers.cpython-39-x86_64-linux-gnu.so
ridepy/util/testing_utils_cython/__init__.py
ridepy/util/testing_utils_cython/dispatchers.pyx
ridepy/util/testing_utils_cython/dispatchers.cpython-39-x86_64-linux-gnu.so
ridepy/util/dispatchers/taxicab.py
ridepy/util/dispatchers/dispatcher_class.py
ridepy/util/dispatchers/ridepooling.py
ridepy/util/dispatchers/__init__.py
ridepy/util/analytics/vehicle.py
ridepy/util/analytics/stops.py
ridepy/util/analytics/__init__.py
ridepy/util/analytics/system.py
ridepy/util/analytics/requests.py
ridepy/util/analytics/events.py
ridepy/util/analytics/plotting.py
ridepy-2.10.1.dist-info/RECORD
ridepy-2.10.1.dist-info/entry_points.txt
ridepy-2.10.1.dist-info/WHEEL
ridepy-2.10.1.dist-info/LICENSE
ridepy-2.10.1.dist-info/top_level.txt
ridepy-2.10.1.dist-info/METADATA
