Metadata-Version: 2.1
Name: ridepy
Version: 2.10.1
Summary: Simulates a dispatching algorithm serving exogenous transportation requests with a fleet of vehicles. Does not simulate the universe, unlike MATSim. Batteries are included.
Author-email: Felix Jung <felix.jung@tu-dresden.de>, Debsankha Manik <dmanik@debsankha.net>
Project-URL: Homepage, https://ridepy.org/
Project-URL: Documentation, https://ridepy.org/
Project-URL: Repository, https://github.com/PhysicsOfMobility/ridepy/
Keywords: simulation,ridepooling,mobility,transport,physics
Classifier: Intended Audience :: Science/Research
Classifier: Development Status :: 5 - Production/Stable
Classifier: License :: OSI Approved :: MIT License
Classifier: Natural Language :: English
Classifier: Programming Language :: Python :: 3.9
Classifier: Programming Language :: Cython
Classifier: Programming Language :: C++
Classifier: Operating System :: POSIX :: Linux
Classifier: Topic :: Scientific/Engineering :: Physics
Requires-Python: ~=3.9
License-File: LICENSE
Requires-Dist: decorator
Requires-Dist: networkx
Requires-Dist: numpy
Requires-Dist: pandas>2.2
Requires-Dist: scipy
Requires-Dist: tabulate
Requires-Dist: notebook
Requires-Dist: jupytext
Requires-Dist: matplotlib
Requires-Dist: Cython>=3
Requires-Dist: loky
Requires-Dist: typer
Requires-Dist: pyarrow
Requires-Dist: tqdm
Provides-Extra: dev
Requires-Dist: black==24.8.0; extra == "dev"
Requires-Dist: commitizen; extra == "dev"
Requires-Dist: pdbpp; extra == "dev"
Requires-Dist: pre-commit; extra == "dev"
Requires-Dist: hypothesis; extra == "dev"
Requires-Dist: pytest; extra == "dev"
Requires-Dist: wheel; extra == "dev"
Requires-Dist: tox; extra == "dev"
Requires-Dist: psutil; extra == "dev"
Requires-Dist: check-manifest; extra == "dev"
Requires-Dist: twine; extra == "dev"
Requires-Dist: build; extra == "dev"
Requires-Dist: auditwheel; extra == "dev"
Requires-Dist: blacken-docs; extra == "dev"
Requires-Dist: pygit2; extra == "dev"
Requires-Dist: tomli; extra == "dev"
Requires-Dist: tomli-w; extra == "dev"
Requires-Dist: packaging; extra == "dev"
Requires-Dist: python-gnupg; extra == "dev"
Requires-Dist: osmnx; extra == "dev"
Provides-Extra: doc
Requires-Dist: recommonmark; extra == "doc"
Requires-Dist: sphinx; extra == "doc"
Requires-Dist: sphinx-rtd-theme; extra == "doc"
Requires-Dist: sphinx-toggleprompt; extra == "doc"
Requires-Dist: sphinx-autodoc-typehints; extra == "doc"
Requires-Dist: myst-nb; extra == "doc"
